joserfc_wrapper/AbstractKeyStorage.py
joserfc_wrapper/Exceptions.py
joserfc_wrapper/StorageFile.py
joserfc_wrapper/StorageVault.py
joserfc_wrapper/WrapJWE.py
joserfc_wrapper/WrapJWK.py
joserfc_wrapper/WrapJWT.py
joserfc_wrapper/__init__.py
joserfc_wrapper/cli/GenJWT.py
joserfc_wrapper/cli/__init__.py
joserfc_wrapper-0.2.3.dist-info/LICENSE
joserfc_wrapper-0.2.3.dist-info/METADATA
joserfc_wrapper-0.2.3.dist-info/WHEEL
joserfc_wrapper-0.2.3.dist-info/entry_points.txt
joserfc_wrapper-0.2.3.dist-info/RECORD
