Metadata-Version: 2.1
Name: joserfc-wrapper
Version: 0.2.3
Summary: joserfc-wrapper is a library for easy use of JWT and automatic management of signature keys.
Author: Lubomir Spacek
Author-email: hexim@hexim.cz
Requires-Python: >=3.10,<4.0
Classifier: License :: OSI Approved :: MIT License
Classifier: Programming Language :: Python :: 3
Classifier: Programming Language :: Python :: 3.10
Classifier: Programming Language :: Python :: 3.11
Classifier: Programming Language :: Python :: 3.12
Requires-Dist: fire (>=0.5.0,<0.6.0)
Requires-Dist: hvac[parser] (>=2.1.0,<3.0.0)
Requires-Dist: joserfc (>=0.9.0,<0.10.0)
Project-URL: Homepage, https://github.com/heximcz/joserfc-wrapper
Project-URL: Issues, https://github.com/heximcz/joserfc-wrapper/issues
